miauth/__init__.py
miauth/cli.py
miauth/util.py
miauth/uuid.py
miauth/mi/__init__.py
miauth/mi/miclient.py
miauth/mi/micommand.py
miauth/mi/micrypto.py
miauth/nb/__init__.py
miauth/nb/nbclient.py
miauth/nb/nbcommand.py
miauth/nb/nbcrypto.py
miauth-0.9.2.dist-info/LICENSE
miauth-0.9.2.dist-info/METADATA
miauth-0.9.2.dist-info/WHEEL
miauth-0.9.2.dist-info/entry_points.txt
miauth-0.9.2.dist-info/top_level.txt
miauth-0.9.2.dist-info/RECORD
