Metadata-Version: 2.1
Name: miauth
Version: 0.9.2
Summary: Authenticate and interact with Xiaomi devices over BLE
Home-page: https://github.com/dnandha/miauth
Author: Daljeet Nandha
Author-email: dalj337@gmail.com
License: GNU AGPL v3
Platform: UNKNOWN
Requires-Python: >=3.6
License-File: LICENSE
Requires-Dist: cryptography (==36.0.0)
Requires-Dist: bluepy (==1.3.0)
